wazzup_client/__init__.py
wazzup_client/_compat.py
wazzup_client/base_client.py
wazzup_client/client.py
wazzup_client/exceptions.py
wazzup_client/legacy_client.py
wazzup_client/pagination.py
wazzup_client/rate_limiter.py
wazzup_client/retry.py
wazzup_client/webhook_events.py
wazzup_client/public/__init__.py
wazzup_client/public/client.py
wazzup_client/public/models.py
wazzup_client/public/schemas.py
wazzup_client/public/endpoints/__init__.py
wazzup_client/public/endpoints/channels.py
wazzup_client/public/endpoints/contacts.py
wazzup_client/public/endpoints/counters.py
wazzup_client/public/endpoints/deals.py
wazzup_client/public/endpoints/iframe.py
wazzup_client/public/endpoints/messages.py
wazzup_client/public/endpoints/pipelines.py
wazzup_client/public/endpoints/users.py
wazzup_client/public/endpoints/webhooks.py
wazzup_client/tech/__init__.py
wazzup_client/tech/client.py
wazzup_client/tech/models.py
wazzup_client/tech/schemas.py
wazzup_client/tech/endpoints/__init__.py
wazzup_client/tech/endpoints/accounts.py
wazzup_client/tech/endpoints/balance.py
wazzup_client/tech/endpoints/channels.py
wazzup_client/tech/endpoints/iframe.py
wazzup_client/tech/endpoints/settings.py
wazzup_client/tech/endpoints/users.py
wazzup_client/tech/endpoints/waba.py
wazzup_client/tech/endpoints/webhooks.py
wazzup_pysdk-0.1.8.dist-info/METADATA
wazzup_pysdk-0.1.8.dist-info/WHEEL
wazzup_pysdk-0.1.8.dist-info/top_level.txt
wazzup_pysdk-0.1.8.dist-info/RECORD
