Metadata-Version: 2.4
Name: wazzup-pysdk
Version: 0.1.8
Summary: Asynchronous Python SDK for the Wazzup public and tech APIs.
Author-email: Your Name <you@example.com>
License: MIT
Classifier: Programming Language :: Python :: 3
Classifier: Programming Language :: Python :: 3 :: Only
Classifier: Programming Language :: Python :: 3.9
Classifier: License :: OSI Approved :: MIT License
Classifier: Operating System :: OS Independent
Requires-Python: >=3.9
Requires-Dist: httpx>=0.27.0
Requires-Dist: pydantic>=2.5
Provides-Extra: dev
Requires-Dist: pytest>=7.4; extra == "dev"
Requires-Dist: anyio>=4.0; extra == "dev"
Requires-Dist: python-dotenv; extra == "dev"
Provides-Extra: webhooks
Requires-Dist: fastapi<1.0,>=0.110; extra == "webhooks"
Requires-Dist: uvicorn[standard]<1.0,>=0.23; extra == "webhooks"
